amqp_rpc_client/__init__.py
amqp_rpc_client-1.3.3.dist-info/LICENSE
amqp_rpc_client-1.3.3.dist-info/METADATA
amqp_rpc_client-1.3.3.dist-info/WHEEL
amqp_rpc_client-1.3.3.dist-info/top_level.txt
amqp_rpc_client-1.3.3.dist-info/RECORD
