Metadata-Version: 2.1
Name: amqp-rpc-client
Version: 1.3.3
Summary: An asynchronous RPC client for message brokers implementing the AMQPv0-9-1 protocol
Home-page: https://github.com/j-suchard/amqp-rpc-client
Author: Jan Eike Suchard
Author-email: jan-eike.suchard@magenta.de
Classifier: Programming Language :: Python :: 3
Classifier: License :: OSI Approved :: BSD License
Classifier: Topic :: Software Development :: Libraries
Classifier: Operating System :: OS Independent
Requires-Python: >=3.6
License-File: LICENSE
Requires-Dist: pika (~=1.2.1)
